iidxbak/__init__.py
iidxbak/base.py
iidxbak/conf.py
iidxbak/core_zip.py
iidxbak/main.py
iidxbak/niam.py
iidxbak/test_keys.py
iidxbak/test_m.py
iidxbak-0.9.6.dist-info/METADATA
iidxbak-0.9.6.dist-info/WHEEL
iidxbak-0.9.6.dist-info/entry_points.txt
iidxbak-0.9.6.dist-info/top_level.txt
iidxbak-0.9.6.dist-info/RECORD
