Metadata-Version: 2.1
Name: iidxbak
Version: 0.9.6
Requires-Dist: click ==8.0.4
Requires-Dist: sh >=1.14.3
Requires-Dist: oss2 ==2.18.3
